Metadata-Version: 2.4
Name: llama-index-readers-bagel
Version: 0.4.1
Summary: llama-index readers bagel integration
Author-email: Your Name <you@example.com>
Maintainer: asif
License-Expression: MIT
License-File: LICENSE
Keywords: bagelDB,database,storage,vector
Requires-Python: <4.0,>=3.10
Requires-Dist: bagel>=0.3.2
Requires-Dist: llama-index-core<0.15,>=0.13.0
